HP_plt.py
LICENSE
README.md
hp_plt.py
setup.py
HP_plt.egg-info/PKG-INFO
HP_plt.egg-info/SOURCES.txt
HP_plt.egg-info/dependency_links.txt
HP_plt.egg-info/top_level.txt
hp_plt.egg-info/PKG-INFO
hp_plt.egg-info/SOURCES.txt
hp_plt.egg-info/dependency_links.txt
hp_plt.egg-info/top_level.txt