Metadata-Version: 2.1
Name: hp-plt
Version: 1.20201232
Summary: hpformula for lyy
Author: lyy
Author-email: 
License: MIT
License-File: LICENSE
